django_actionable_messages/__init__.py
django_actionable_messages/elements.py
django_actionable_messages/encoders.py
django_actionable_messages/exceptions.py
django_actionable_messages/mixins.py
django_actionable_messages/settings.py
django_actionable_messages/adaptive_card/__init__.py
django_actionable_messages/adaptive_card/actions.py
django_actionable_messages/adaptive_card/cards.py
django_actionable_messages/adaptive_card/containers.py
django_actionable_messages/adaptive_card/elements.py
django_actionable_messages/adaptive_card/inputs.py
django_actionable_messages/adaptive_card/mixins.py
django_actionable_messages/adaptive_card/types.py
django_actionable_messages/adaptive_card/utils.py
django_actionable_messages/adaptive_card/outlook/__init__.py
django_actionable_messages/adaptive_card/outlook/actions.py
django_actionable_messages/adaptive_card/outlook/containers.py
django_actionable_messages/adaptive_card/outlook/mixins.py
django_actionable_messages/message_card/__init__.py
django_actionable_messages/message_card/actions.py
django_actionable_messages/message_card/cards.py
django_actionable_messages/message_card/elements.py
django_actionable_messages/message_card/inputs.py
django_actionable_messages/message_card/mixins.py
django_actionable_messages/message_card/sections.py
django_actionable_messages/message_card/utils.py
django_actionable_messages/msteams_cards/__init__.py
django_actionable_messages/msteams_cards/cards.py
django_actionable_messages/msteams_cards/elements.py
django_actionable_messages/msteams_cards/mixins.py
django_actionable_messages/templates/django_actionable_messages/email.html
django_actionable_messages/templates/django_actionable_messages/signed_email.html
django_actionable_messages-0.2.7.dist-info/LICENSE
django_actionable_messages-0.2.7.dist-info/METADATA
django_actionable_messages-0.2.7.dist-info/WHEEL
django_actionable_messages-0.2.7.dist-info/top_level.txt
django_actionable_messages-0.2.7.dist-info/RECORD
