Metadata-Version: 2.1
Name: django-actionable-messages
Version: 0.2.7
Summary: Actionable messages
Home-page: https://github.com/utsurius/django-actionable-messages
Author: utsurius
Author-email: przemek@upsecure.pl
License: MIT
Project-URL: Documentation, https://github.com/utsurius/django-actionable-messages/blob/master/README.md
Project-URL: Source, https://github.com/utsurius/django-actionable-messages
Project-URL: Tracker, https://github.com/utsurius/django-actionable-messages/issues
Keywords: msteams,AdaptiveCard,MessageCard,HeroCard,ThumbnailCard,actionable messages
Classifier: Development Status :: 4 - Beta
Classifier: Environment :: Web Environment
Classifier: Framework :: Django
Classifier: Framework :: Django :: 3.2
Classifier: Framework :: Django :: 4.0
Classifier: Framework :: Django :: 4.1
Classifier: Framework :: Django :: 4.2
Classifier: Intended Audience :: Developers
Classifier: License :: OSI Approved :: MIT License
Classifier: Operating System :: OS Independent
Classifier: Programming Language :: Python :: 3 :: Only
Classifier: Programming Language :: Python :: 3.6
Classifier: Programming Language :: Python :: 3.7
Classifier: Programming Language :: Python :: 3.8
Classifier: Programming Language :: Python :: 3.9
Classifier: Programming Language :: Python :: 3.10
Classifier: Topic :: Software Development :: Libraries :: Python Modules
Requires-Python: >=3.6
License-File: LICENSE
Requires-Dist: django >=3.2.0
